collective.plausible-1.0a6-py3.10-nspkg.pth
collective/plausible/__init__.py
collective/plausible/configure.zcml
collective/plausible/interfaces.py
collective/plausible/permissions.zcml
collective/plausible/setuphandlers.py
collective/plausible/testing.py
collective/plausible/utils.py
collective/plausible/behaviors/__init__.py
collective/plausible/behaviors/configure.zcml
collective/plausible/behaviors/plausible_fields.py
collective/plausible/browser/__init__.py
collective/plausible/browser/configure.zcml
collective/plausible/browser/overrides/.gitkeep
collective/plausible/browser/static/.gitkeep
collective/plausible/controlpanels/__init__.py
collective/plausible/controlpanels/configure.zcml
collective/plausible/controlpanels/plausible_control_panel/__init__.py
collective/plausible/controlpanels/plausible_control_panel/configure.zcml
collective/plausible/controlpanels/plausible_control_panel/controlpanel.pt
collective/plausible/controlpanels/plausible_control_panel/controlpanel.py
collective/plausible/locales/README.rst
collective/plausible/locales/__init__.py
collective/plausible/locales/collective.plausible.pot
collective/plausible/locales/update.py
collective/plausible/locales/update.sh
collective/plausible/locales/en/LC_MESSAGES/collective.plausible.po
collective/plausible/locales/fr/LC_MESSAGES/collective.plausible.po
collective/plausible/profiles/default/actions.xml
collective/plausible/profiles/default/browserlayer.xml
collective/plausible/profiles/default/catalog.xml
collective/plausible/profiles/default/controlpanel.xml
collective/plausible/profiles/default/metadata.xml
collective/plausible/profiles/default/rolemap.xml
collective/plausible/profiles/default/registry/main.xml
collective/plausible/profiles/default/registry/plausible_control_panel.xml
collective/plausible/profiles/testing/types/Document.xml
collective/plausible/profiles/testing/types/Folder.xml
collective/plausible/profiles/uninstall/browserlayer.xml
collective/plausible/tests/__init__.py
collective.plausible-1.0a6.dist-info/LICENSE.GPL
collective.plausible-1.0a6.dist-info/LICENSE.rst
collective.plausible-1.0a6.dist-info/METADATA
collective.plausible-1.0a6.dist-info/WHEEL
collective.plausible-1.0a6.dist-info/entry_points.txt
collective.plausible-1.0a6.dist-info/namespace_packages.txt
collective.plausible-1.0a6.dist-info/top_level.txt
collective.plausible-1.0a6.dist-info/RECORD
